kof_notebooklm_mcp/__init__.py
kof_notebooklm_mcp/cli.py
kof_notebooklm_mcp/config.py
kof_notebooklm_mcp/server.py
kof_notebooklm_mcp/client/__init__.py
kof_notebooklm_mcp/client/browser.py
kof_notebooklm_mcp/client/session.py
kof_notebooklm_mcp/client/pages/__init__.py
kof_notebooklm_mcp/client/pages/base.py
kof_notebooklm_mcp/client/pages/notebook_detail.py
kof_notebooklm_mcp/client/pages/notebooks.py
kof_notebooklm_mcp/tools/__init__.py
kof_notebooklm_mcp/tools/add_source.py
kof_notebooklm_mcp/tools/ask.py
kof_notebooklm_mcp/tools/create_notebook.py
kof_notebooklm_mcp/tools/get_notebook.py
kof_notebooklm_mcp/tools/health_check.py
kof_notebooklm_mcp/tools/list_notebooks.py
kof_notebooklm_mcp/tools/list_sources.py
kof_notebooklm_mcp/utils/__init__.py
kof_notebooklm_mcp/utils/circuit_breaker.py
kof_notebooklm_mcp/utils/errors.py
kof_notebooklm_mcp/utils/rate_limit.py
kof_notebooklm_mcp/utils/retry.py
kof_notebooklm_mcp/utils/validation.py
kof_notebooklm_mcp-0.1.1.dist-info/METADATA
kof_notebooklm_mcp-0.1.1.dist-info/WHEEL
kof_notebooklm_mcp-0.1.1.dist-info/entry_points.txt
kof_notebooklm_mcp-0.1.1.dist-info/licenses/LICENSE
kof_notebooklm_mcp-0.1.1.dist-info/RECORD
