Metadata-Version: 2.4
Name: kof-notebooklm-mcp
Version: 0.1.1
Summary: MCP server for Google NotebookLM - Create notebooks, add sources, and query AI with citations
Project-URL: Homepage, https://github.com/keeponfirst/kof-notebooklm-mcp
Project-URL: Documentation, https://github.com/keeponfirst/kof-notebooklm-mcp#readme
Project-URL: Repository, https://github.com/keeponfirst/kof-notebooklm-mcp
Project-URL: Issues, https://github.com/keeponfirst/kof-notebooklm-mcp/issues
Author-email: KeepOnFirst <keeponfirst@example.com>
License-Expression: MIT
License-File: LICENSE
Keywords: ai,google,knowledge-management,mcp,model-context-protocol,notebooklm
Classifier: Development Status :: 3 - Alpha
Classifier: Intended Audience :: Developers
Classifier: License :: OSI Approved :: MIT License
Classifier: Programming Language :: Python :: 3
Classifier: Programming Language :: Python :: 3.10
Classifier: Programming Language :: Python :: 3.11
Classifier: Programming Language :: Python :: 3.12
Classifier: Programming Language :: Python :: 3.13
Requires-Python: >=3.10
Requires-Dist: mcp>=1.0.0
Requires-Dist: playwright>=1.40.0
Requires-Dist: pydantic>=2.0.0
Requires-Dist: python-dotenv>=1.0.0
Provides-Extra: dev
Requires-Dist: mypy>=1.0.0; extra == 'dev'
Requires-Dist: pytest-asyncio>=0.21.0; extra == 'dev'
Requires-Dist: pytest-cov>=4.0.0; extra == 'dev'
Requires-Dist: pytest>=7.0.0; extra == 'dev'
Requires-Dist: ruff>=0.1.0; extra == 'dev'
